AUTHORS.rst
CONTRIBUTING.rst
HISTORY.rst
LICENSE
MANIFEST.in
README.rst
setup.cfg
setup.py
connected_accounts/__init__.py
connected_accounts/admin.py
connected_accounts/apps.py
connected_accounts/conf.py
connected_accounts/fields.py
connected_accounts/forms.py
connected_accounts/models.py
connected_accounts/provider_pool.py
connected_accounts/views.py
connected_accounts/widgets.py
connected_accounts/migrations/0001_initial.py
connected_accounts/migrations/__init__.py
connected_accounts/providers/__init__.py
connected_accounts/providers/base.py
connected_accounts/providers/bitly.py
connected_accounts/providers/disqus.py
connected_accounts/providers/facebook.py
connected_accounts/providers/google.py
connected_accounts/providers/instagram.py
connected_accounts/providers/mailchimp.py
connected_accounts/providers/twitter.py
connected_accounts/south_migrations/0001_initial.py
connected_accounts/south_migrations/__init__.py
connected_accounts/static/css/connected_accounts/admin/connected_accounts.css
connected_accounts/static/img/connected_accounts/icon-user-default.jpg
connected_accounts/static/img/connected_accounts/icon_deletelink.png
connected_accounts/static/img/connected_accounts/icon_searchbox.png
connected_accounts/static/img/connected_accounts/providers/bitly.png
connected_accounts/static/img/connected_accounts/providers/mailchimp.png
connected_accounts/static/js/connected_accounts/connected_accounts.js
connected_accounts/static/js/connected_accounts/admin/widgets.js
connected_accounts/templates/admin/connected_accounts/account/change_form.html
connected_accounts/templates/admin/connected_accounts/account/change_list.html
connected_accounts/templates/admin/connected_accounts/account/includes/changelist_avatar.html
connected_accounts/templates/admin/connected_accounts/account/widgets/account_widget.html
django_connected.egg-info/PKG-INFO
django_connected.egg-info/SOURCES.txt
django_connected.egg-info/dependency_links.txt
django_connected.egg-info/not-zip-safe
django_connected.egg-info/requires.txt
django_connected.egg-info/top_level.txt