Metadata-Version: 1.1
Name: django-connected
Version: 0.1.5
Summary: Connect your Django powered sites to social networks and other online services.
Home-page: https://github.com/mishbahr/django-connected
Author: Mishbah Razzaque
Author-email: mishbahx@gmail.com
License: BSD
Keywords: django-connected,social auth,oauth,oauth2,facebook,twitter,google
Platform: UNKNOWN
Classifier: Development Status :: 4 - Beta
Classifier: Framework :: Django
Classifier: Intended Audience :: Developers
Classifier: License :: OSI Approved :: BSD License
Classifier: Natural Language :: English
Classifier: Programming Language :: Python :: 2
Classifier: Programming Language :: Python :: 2.6
Classifier: Programming Language :: Python :: 2.7
Classifier: Programming Language :: Python :: 3
Classifier: Programming Language :: Python :: 3.3
